<annotation>
	<folder>OPTIMAL_Z</folder>
	<filename>00019.jpg</filename>
	<source>
		<database>The OPTIMAL_Z Database</database>
		<annotation>OPTIMAL_Z_anno</annotation>
		<image>OPTIMAL_Z_img</image>
		<flickrid>NULL</flickrid>
	</source>
	<owner>
		<flickrid>NULL</flickrid>
		<name>snail_crowling</name>
	</owner>
	<size>
		<width>1597</width>
		<height>1837</height>
		<depth>3</depth>
	</size>
	<segmented>0</segmented>
	<object>
		<name>airplane</name>
		<pose>overlook</pose>
		<truncated>0</truncated>
		<difficult>0</difficult>
		<bndbox>
			<xmin>1263</xmin>
			<ymin>839</ymin>
			<xmax>1476</xmax>
			<ymax>1032</ymax>
		</bndbox>
	</object>
	<object>
		<name>airplane</name>
		<pose>overlook</pose>
		<truncated>0</truncated>
		<difficult>0</difficult>
		<bndbox>
			<xmin>1257</xmin>
			<ymin>659</ymin>
			<xmax>1347</xmax>
			<ymax>749</ymax>
		</bndbox>
	</object>
	<object>
		<name>airplane</name>
		<pose>overlook</pose>
		<truncated>0</truncated>
		<difficult>0</difficult>
		<bndbox>
			<xmin>885</xmin>
			<ymin>989</ymin>
			<xmax>960</xmax>
			<ymax>1070</ymax>
		</bndbox>
	</object>
	<object>
		<name>airplane</name>
		<pose>overlook</pose>
		<truncated>0</truncated>
		<difficult>0</difficult>
		<bndbox>
			<xmin>900</xmin>
			<ymin>1095</ymin>
			<xmax>972</xmax>
			<ymax>1175</ymax>
		</bndbox>
	</object>
	<object>
		<name>airplane</name>
		<pose>overlook</pose>
		<truncated>0</truncated>
		<difficult>0</difficult>
		<bndbox>
			<xmin>914</xmin>
			<ymin>1202</ymin>
			<xmax>1002</xmax>
			<ymax>1287</ymax>
		</bndbox>
	</object>
	<object>
		<name>airplane</name>
		<pose>overlook</pose>
		<truncated>0</truncated>
		<difficult>0</difficult>
		<bndbox>
			<xmin>941</xmin>
			<ymin>1423</ymin>
			<xmax>1019</xmax>
			<ymax>1501</ymax>
		</bndbox>
	</object>
</annotation>
