<annotation>
	<folder>OPTIMAL_Z</folder>
	<filename>00162.jpg</filename>
	<source>
		<database>The OPTIMAL_Z Database</database>
		<annotation>OPTIMAL_Z_anno</annotation>
		<image>OPTIMAL_Z_img</image>
		<flickrid>NULL</flickrid>
	</source>
	<owner>
		<flickrid>NULL</flickrid>
		<name>snail_crowling</name>
	</owner>
	<size>
		<width>1200</width>
		<height>836</height>
		<depth>3</depth>
	</size>
	<segmented>0</segmented>
	<object>
		<name>ship</name>
		<pose>overlook</pose>
		<truncated>0</truncated>
		<difficult>0</difficult>
		<bndbox>
			<xmin>11</xmin>
			<ymin>360</ymin>
			<xmax>187</xmax>
			<ymax>459</ymax>
		</bndbox>
	</object>
	<object>
		<name>storage tank</name>
		<pose>overlook</pose>
		<truncated>0</truncated>
		<difficult>0</difficult>
		<bndbox>
			<xmin>676</xmin>
			<ymin>473</ymin>
			<xmax>744</xmax>
			<ymax>545</ymax>
		</bndbox>
	</object>
	<object>
		<name>storage tank</name>
		<pose>overlook</pose>
		<truncated>0</truncated>
		<difficult>0</difficult>
		<bndbox>
			<xmin>753</xmin>
			<ymin>471</ymin>
			<xmax>823</xmax>
			<ymax>546</ymax>
		</bndbox>
	</object>
	<object>
		<name>storage tank</name>
		<pose>overlook</pose>
		<truncated>0</truncated>
		<difficult>0</difficult>
		<bndbox>
			<xmin>825</xmin>
			<ymin>429</ymin>
			<xmax>891</xmax>
			<ymax>492</ymax>
		</bndbox>
	</object>
	<object>
		<name>storage tank</name>
		<pose>overlook</pose>
		<truncated>0</truncated>
		<difficult>0</difficult>
		<bndbox>
			<xmin>681</xmin>
			<ymin>566</ymin>
			<xmax>795</xmax>
			<ymax>693</ymax>
		</bndbox>
	</object>
	<object>
		<name>storage tank</name>
		<pose>overlook</pose>
		<truncated>0</truncated>
		<difficult>0</difficult>
		<bndbox>
			<xmin>678</xmin>
			<ymin>707</ymin>
			<xmax>801</xmax>
			<ymax>824</ymax>
		</bndbox>
	</object>
	<object>
		<name>storage tank</name>
		<pose>overlook</pose>
		<truncated>0</truncated>
		<difficult>0</difficult>
		<bndbox>
			<xmin>813</xmin>
			<ymin>705</ymin>
			<xmax>928</xmax>
			<ymax>824</ymax>
		</bndbox>
	</object>
	<object>
		<name>storage tank</name>
		<pose>overlook</pose>
		<truncated>0</truncated>
		<difficult>0</difficult>
		<bndbox>
			<xmin>807</xmin>
			<ymin>564</ymin>
			<xmax>930</xmax>
			<ymax>690</ymax>
		</bndbox>
	</object>
	<object>
		<name>storage tank</name>
		<pose>overlook</pose>
		<truncated>0</truncated>
		<difficult>0</difficult>
		<bndbox>
			<xmin>942</xmin>
			<ymin>564</ymin>
			<xmax>1070</xmax>
			<ymax>692</ymax>
		</bndbox>
	</object>
	<object>
		<name>storage tank</name>
		<pose>overlook</pose>
		<truncated>0</truncated>
		<difficult>0</difficult>
		<bndbox>
			<xmin>940</xmin>
			<ymin>699</ymin>
			<xmax>1076</xmax>
			<ymax>827</ymax>
		</bndbox>
	</object>
</annotation>
