<annotation>
	<folder>OPTIMAL_Z</folder>
	<filename>00302.jpg</filename>
	<source>
		<database>The OPTIMAL_Z Database</database>
		<annotation>OPTIMAL_Z_anno</annotation>
		<image>OPTIMAL_Z_img</image>
		<flickrid>NULL</flickrid>
	</source>
	<owner>
		<flickrid>NULL</flickrid>
		<name>snail_crowling</name>
	</owner>
	<size>
		<width>1922</width>
		<height>1838</height>
		<depth>3</depth>
	</size>
	<segmented>0</segmented>
	<object>
		<name>baseball diamond</name>
		<pose>overlook</pose>
		<truncated>0</truncated>
		<difficult>0</difficult>
		<bndbox>
			<xmin>453</xmin>
			<ymin>525</ymin>
			<xmax>707</xmax>
			<ymax>768</ymax>
		</bndbox>
	</object>
	<object>
		<name>tennis court</name>
		<pose>overlook</pose>
		<truncated>0</truncated>
		<difficult>0</difficult>
		<bndbox>
			<xmin>1514</xmin>
			<ymin>1484</ymin>
			<xmax>1609</xmax>
			<ymax>1592</ymax>
		</bndbox>
	</object>
	<object>
		<name>tennis court</name>
		<pose>overlook</pose>
		<truncated>0</truncated>
		<difficult>0</difficult>
		<bndbox>
			<xmin>1556</xmin>
			<ymin>1509</ymin>
			<xmax>1653</xmax>
			<ymax>1624</ymax>
		</bndbox>
	</object>
	<object>
		<name>tennis court</name>
		<pose>overlook</pose>
		<truncated>0</truncated>
		<difficult>0</difficult>
		<bndbox>
			<xmin>1601</xmin>
			<ymin>1541</ymin>
			<xmax>1699</xmax>
			<ymax>1650</ymax>
		</bndbox>
	</object>
	<object>
		<name>tennis court</name>
		<pose>overlook</pose>
		<truncated>0</truncated>
		<difficult>0</difficult>
		<bndbox>
			<xmin>1643</xmin>
			<ymin>1570</ymin>
			<xmax>1745</xmax>
			<ymax>1684</ymax>
		</bndbox>
	</object>
</annotation>
