<annotation>
	<folder>OPTIMAL_Z</folder>
	<filename>00397.jpg</filename>
	<source>
		<database>The OPTIMAL_Z Database</database>
		<annotation>OPTIMAL_Z_anno</annotation>
		<image>OPTIMAL_Z_img</image>
		<flickrid>NULL</flickrid>
	</source>
	<owner>
		<flickrid>NULL</flickrid>
		<name>snail_crowling</name>
	</owner>
	<size>
		<width>2315</width>
		<height>1727</height>
		<depth>3</depth>
	</size>
	<segmented>0</segmented>
	<object>
		<name>airplane</name>
		<pose>overlook</pose>
		<truncated>0</truncated>
		<difficult>0</difficult>
		<bndbox>
			<xmin>539</xmin>
			<ymin>104</ymin>
			<xmax>854</xmax>
			<ymax>371</ymax>
		</bndbox>
	</object>
	<object>
		<name>airplane</name>
		<pose>overlook</pose>
		<truncated>0</truncated>
		<difficult>0</difficult>
		<bndbox>
			<xmin>707</xmin>
			<ymin>404</ymin>
			<xmax>989</xmax>
			<ymax>647</ymax>
		</bndbox>
	</object>
	<object>
		<name>airplane</name>
		<pose>overlook</pose>
		<truncated>0</truncated>
		<difficult>0</difficult>
		<bndbox>
			<xmin>1151</xmin>
			<ymin>1138</ymin>
			<xmax>1462</xmax>
			<ymax>1408</ymax>
		</bndbox>
	</object>
	<object>
		<name>airplane</name>
		<pose>overlook</pose>
		<truncated>0</truncated>
		<difficult>0</difficult>
		<bndbox>
			<xmin>1285</xmin>
			<ymin>1420</ymin>
			<xmax>1603</xmax>
			<ymax>1708</ymax>
		</bndbox>
	</object>
	<object>
		<name>airplane</name>
		<pose>overlook</pose>
		<truncated>0</truncated>
		<difficult>0</difficult>
		<bndbox>
			<xmin>2037</xmin>
			<ymin>1082</ymin>
			<xmax>2184</xmax>
			<ymax>1223</ymax>
		</bndbox>
	</object>
</annotation>
