<annotation>
	<folder>OPTIMAL_Z</folder>
	<filename>00930.jpg</filename>
	<source>
		<database>The OPTIMAL_Z Database</database>
		<annotation>OPTIMAL_Z_anno</annotation>
		<image>OPTIMAL_Z_img</image>
		<flickrid>NULL</flickrid>
	</source>
	<owner>
		<flickrid>NULL</flickrid>
		<name>snail_crowling</name>
	</owner>
	<size>
		<width>928</width>
		<height>624</height>
		<depth>3</depth>
	</size>
	<segmented>0</segmented>
	<object>
		<name>baseball diamond</name>
		<pose>overlook</pose>
		<truncated>0</truncated>
		<difficult>0</difficult>
		<bndbox>
			<xmin>418</xmin>
			<ymin>282</ymin>
			<xmax>824</xmax>
			<ymax>607</ymax>
		</bndbox>
	</object>
	<object>
		<name>tennis court</name>
		<pose>overlook</pose>
		<truncated>0</truncated>
		<difficult>0</difficult>
		<bndbox>
			<xmin>708</xmin>
			<ymin>111</ymin>
			<xmax>825</xmax>
			<ymax>213</ymax>
		</bndbox>
	</object>
	<object>
		<name>tennis court</name>
		<pose>overlook</pose>
		<truncated>0</truncated>
		<difficult>0</difficult>
		<bndbox>
			<xmin>739</xmin>
			<ymin>169</ymin>
			<xmax>857</xmax>
			<ymax>270</ymax>
		</bndbox>
	</object>
	<object>
		<name>tennis court</name>
		<pose>overlook</pose>
		<truncated>0</truncated>
		<difficult>0</difficult>
		<bndbox>
			<xmin>771</xmin>
			<ymin>227</ymin>
			<xmax>889</xmax>
			<ymax>325</ymax>
		</bndbox>
	</object>
</annotation>
