<annotation>
	<folder>OPTIMAL_Z</folder>
	<filename>01048.jpg</filename>
	<source>
		<database>The OPTIMAL_Z Database</database>
		<annotation>OPTIMAL_Z_anno</annotation>
		<image>OPTIMAL_Z_img</image>
		<flickrid>NULL</flickrid>
	</source>
	<owner>
		<flickrid>NULL</flickrid>
		<name>snail_crowling</name>
	</owner>
	<size>
		<width>783</width>
		<height>538</height>
		<depth>3</depth>
	</size>
	<segmented>0</segmented>
	<object>
		<name>storage tank</name>
		<pose>overlook</pose>
		<truncated>0</truncated>
		<difficult>0</difficult>
		<bndbox>
			<xmin>8</xmin>
			<ymin>8</ymin>
			<xmax>176</xmax>
			<ymax>166</ymax>
		</bndbox>
	</object>
	<object>
		<name>storage tank</name>
		<pose>overlook</pose>
		<truncated>0</truncated>
		<difficult>0</difficult>
		<bndbox>
			<xmin>227</xmin>
			<ymin>75</ymin>
			<xmax>404</xmax>
			<ymax>242</ymax>
		</bndbox>
	</object>
	<object>
		<name>storage tank</name>
		<pose>overlook</pose>
		<truncated>0</truncated>
		<difficult>0</difficult>
		<bndbox>
			<xmin>514</xmin>
			<ymin>74</ymin>
			<xmax>757</xmax>
			<ymax>309</ymax>
		</bndbox>
	</object>
	<object>
		<name>storage tank</name>
		<pose>overlook</pose>
		<truncated>0</truncated>
		<difficult>0</difficult>
		<bndbox>
			<xmin>317</xmin>
			<ymin>270</ymin>
			<xmax>508</xmax>
			<ymax>454</ymax>
		</bndbox>
	</object>
	<object>
		<name>storage tank</name>
		<pose>overlook</pose>
		<truncated>0</truncated>
		<difficult>0</difficult>
		<bndbox>
			<xmin>30</xmin>
			<ymin>270</ymin>
			<xmax>221</xmax>
			<ymax>453</ymax>
		</bndbox>
	</object>
</annotation>
