<annotation>
	<folder>OPTIMAL_Z</folder>
	<filename>01782.jpg</filename>
	<source>
		<database>The OPTIMAL_Z Database</database>
		<annotation>OPTIMAL_Z_anno</annotation>
		<image>OPTIMAL_Z_img</image>
		<flickrid>NULL</flickrid>
	</source>
	<owner>
		<flickrid>NULL</flickrid>
		<name>snail_crowling</name>
	</owner>
	<size>
		<width>739</width>
		<height>754</height>
		<depth>3</depth>
	</size>
	<segmented>0</segmented>
	<object>
		<name>tennis court</name>
		<pose>overlook</pose>
		<truncated>0</truncated>
		<difficult>0</difficult>
		<bndbox>
			<xmin>48</xmin>
			<ymin>337</ymin>
			<xmax>158</xmax>
			<ymax>483</ymax>
		</bndbox>
	</object>
	<object>
		<name>tennis court</name>
		<pose>overlook</pose>
		<truncated>0</truncated>
		<difficult>0</difficult>
		<bndbox>
			<xmin>120</xmin>
			<ymin>306</ymin>
			<xmax>228</xmax>
			<ymax>452</ymax>
		</bndbox>
	</object>
	<object>
		<name>tennis court</name>
		<pose>overlook</pose>
		<truncated>0</truncated>
		<difficult>0</difficult>
		<bndbox>
			<xmin>191</xmin>
			<ymin>274</ymin>
			<xmax>300</xmax>
			<ymax>418</ymax>
		</bndbox>
	</object>
	<object>
		<name>tennis court</name>
		<pose>overlook</pose>
		<truncated>0</truncated>
		<difficult>0</difficult>
		<bndbox>
			<xmin>130</xmin>
			<ymin>517</ymin>
			<xmax>238</xmax>
			<ymax>661</ymax>
		</bndbox>
	</object>
	<object>
		<name>tennis court</name>
		<pose>overlook</pose>
		<truncated>0</truncated>
		<difficult>0</difficult>
		<bndbox>
			<xmin>200</xmin>
			<ymin>486</ymin>
			<xmax>310</xmax>
			<ymax>631</ymax>
		</bndbox>
	</object>
	<object>
		<name>tennis court</name>
		<pose>overlook</pose>
		<truncated>0</truncated>
		<difficult>0</difficult>
		<bndbox>
			<xmin>271</xmin>
			<ymin>455</ymin>
			<xmax>380</xmax>
			<ymax>596</ymax>
		</bndbox>
	</object>
</annotation>
