<annotation>
	<folder>OPTIMAL_Z</folder>
	<filename>02021.jpg</filename>
	<source>
		<database>The OPTIMAL_Z Database</database>
		<annotation>OPTIMAL_Z_anno</annotation>
		<image>OPTIMAL_Z_img</image>
		<flickrid>NULL</flickrid>
	</source>
	<owner>
		<flickrid>NULL</flickrid>
		<name>snail_crowling</name>
	</owner>
	<size>
		<width>860</width>
		<height>690</height>
		<depth>3</depth>
	</size>
	<segmented>0</segmented>
	<object>
		<name>tennis court</name>
		<pose>overlook</pose>
		<truncated>0</truncated>
		<difficult>0</difficult>
		<bndbox>
			<xmin>584</xmin>
			<ymin>186</ymin>
			<xmax>714</xmax>
			<ymax>323</ymax>
		</bndbox>
	</object>
	<object>
		<name>tennis court</name>
		<pose>overlook</pose>
		<truncated>0</truncated>
		<difficult>0</difficult>
		<bndbox>
			<xmin>525</xmin>
			<ymin>241</ymin>
			<xmax>658</xmax>
			<ymax>378</ymax>
		</bndbox>
	</object>
	<object>
		<name>tennis court</name>
		<pose>overlook</pose>
		<truncated>0</truncated>
		<difficult>0</difficult>
		<bndbox>
			<xmin>465</xmin>
			<ymin>290</ymin>
			<xmax>600</xmax>
			<ymax>431</ymax>
		</bndbox>
	</object>
	<object>
		<name>tennis court</name>
		<pose>overlook</pose>
		<truncated>0</truncated>
		<difficult>0</difficult>
		<bndbox>
			<xmin>404</xmin>
			<ymin>348</ymin>
			<xmax>541</xmax>
			<ymax>484</ymax>
		</bndbox>
	</object>
	<object>
		<name>tennis court</name>
		<pose>overlook</pose>
		<truncated>0</truncated>
		<difficult>0</difficult>
		<bndbox>
			<xmin>347</xmin>
			<ymin>399</ymin>
			<xmax>482</xmax>
			<ymax>536</ymax>
		</bndbox>
	</object>
	<object>
		<name>tennis court</name>
		<pose>overlook</pose>
		<truncated>0</truncated>
		<difficult>0</difficult>
		<bndbox>
			<xmin>718</xmin>
			<ymin>332</ymin>
			<xmax>849</xmax>
			<ymax>470</ymax>
		</bndbox>
	</object>
	<object>
		<name>tennis court</name>
		<pose>overlook</pose>
		<truncated>0</truncated>
		<difficult>0</difficult>
		<bndbox>
			<xmin>659</xmin>
			<ymin>382</ymin>
			<xmax>793</xmax>
			<ymax>522</ymax>
		</bndbox>
	</object>
	<object>
		<name>tennis court</name>
		<pose>overlook</pose>
		<truncated>0</truncated>
		<difficult>0</difficult>
		<bndbox>
			<xmin>601</xmin>
			<ymin>437</ymin>
			<xmax>734</xmax>
			<ymax>576</ymax>
		</bndbox>
	</object>
	<object>
		<name>tennis court</name>
		<pose>overlook</pose>
		<truncated>0</truncated>
		<difficult>0</difficult>
		<bndbox>
			<xmin>544</xmin>
			<ymin>491</ymin>
			<xmax>676</xmax>
			<ymax>628</ymax>
		</bndbox>
	</object>
	<object>
		<name>tennis court</name>
		<pose>overlook</pose>
		<truncated>0</truncated>
		<difficult>0</difficult>
		<bndbox>
			<xmin>483</xmin>
			<ymin>545</ymin>
			<xmax>618</xmax>
			<ymax>681</ymax>
		</bndbox>
	</object>
</annotation>
