<annotation>
	<folder>OPTIMAL_Z</folder>
	<filename>02147.jpg</filename>
	<source>
		<database>The OPTIMAL_Z Database</database>
		<annotation>OPTIMAL_Z_anno</annotation>
		<image>OPTIMAL_Z_img</image>
		<flickrid>NULL</flickrid>
	</source>
	<owner>
		<flickrid>NULL</flickrid>
		<name>snail_crowling</name>
	</owner>
	<size>
		<width>706</width>
		<height>485</height>
		<depth>3</depth>
	</size>
	<segmented>0</segmented>
	<object>
		<name>tennis court</name>
		<pose>overlook</pose>
		<truncated>0</truncated>
		<difficult>0</difficult>
		<bndbox>
			<xmin>56</xmin>
			<ymin>148</ymin>
			<xmax>171</xmax>
			<ymax>294</ymax>
		</bndbox>
	</object>
	<object>
		<name>tennis court</name>
		<pose>overlook</pose>
		<truncated>0</truncated>
		<difficult>0</difficult>
		<bndbox>
			<xmin>119</xmin>
			<ymin>110</ymin>
			<xmax>237</xmax>
			<ymax>255</ymax>
		</bndbox>
	</object>
	<object>
		<name>tennis court</name>
		<pose>overlook</pose>
		<truncated>0</truncated>
		<difficult>0</difficult>
		<bndbox>
			<xmin>183</xmin>
			<ymin>71</ymin>
			<xmax>303</xmax>
			<ymax>216</ymax>
		</bndbox>
	</object>
	<object>
		<name>tennis court</name>
		<pose>overlook</pose>
		<truncated>0</truncated>
		<difficult>0</difficult>
		<bndbox>
			<xmin>251</xmin>
			<ymin>34</ymin>
			<xmax>367</xmax>
			<ymax>179</ymax>
		</bndbox>
	</object>
</annotation>
