<annotation>
	<folder>OPTIMAL_Z</folder>
	<filename>03330.jpg</filename>
	<source>
		<database>The OPTIMAL_Z Database</database>
		<annotation>OPTIMAL_Z_anno</annotation>
		<image>OPTIMAL_Z_img</image>
		<flickrid>NULL</flickrid>
	</source>
	<owner>
		<flickrid>NULL</flickrid>
		<name>snail_crowling</name>
	</owner>
	<size>
		<width>858</width>
		<height>558</height>
		<depth>3</depth>
	</size>
	<segmented>0</segmented>
	<object>
		<name>airplane</name>
		<pose>overlook</pose>
		<truncated>0</truncated>
		<difficult>0</difficult>
		<bndbox>
			<xmin>415</xmin>
			<ymin>288</ymin>
			<xmax>581</xmax>
			<ymax>470</ymax>
		</bndbox>
	</object>
	<object>
		<name>airplane</name>
		<pose>overlook</pose>
		<truncated>0</truncated>
		<difficult>0</difficult>
		<bndbox>
			<xmin>248</xmin>
			<ymin>340</ymin>
			<xmax>404</xmax>
			<ymax>528</ymax>
		</bndbox>
	</object>
	<object>
		<name>airplane</name>
		<pose>overlook</pose>
		<truncated>0</truncated>
		<difficult>0</difficult>
		<bndbox>
			<xmin>117</xmin>
			<ymin>323</ymin>
			<xmax>257</xmax>
			<ymax>468</ymax>
		</bndbox>
	</object>
	<object>
		<name>airplane</name>
		<pose>overlook</pose>
		<truncated>0</truncated>
		<difficult>0</difficult>
		<bndbox>
			<xmin>105</xmin>
			<ymin>121</ymin>
			<xmax>238</xmax>
			<ymax>258</ymax>
		</bndbox>
	</object>
</annotation>
