<annotation>
	<folder>OPTIMAL_Z</folder>
	<filename>03499.jpg</filename>
	<source>
		<database>The OPTIMAL_Z Database</database>
		<annotation>OPTIMAL_Z_anno</annotation>
		<image>OPTIMAL_Z_img</image>
		<flickrid>NULL</flickrid>
	</source>
	<owner>
		<flickrid>NULL</flickrid>
		<name>snail_crowling</name>
	</owner>
	<size>
		<width>930</width>
		<height>672</height>
		<depth>3</depth>
	</size>
	<segmented>0</segmented>
	<object>
		<name>storage tank</name>
		<pose>overlook</pose>
		<truncated>0</truncated>
		<difficult>0</difficult>
		<bndbox>
			<xmin>124</xmin>
			<ymin>3</ymin>
			<xmax>263</xmax>
			<ymax>136</ymax>
		</bndbox>
	</object>
	<object>
		<name>storage tank</name>
		<pose>overlook</pose>
		<truncated>0</truncated>
		<difficult>0</difficult>
		<bndbox>
			<xmin>348</xmin>
			<ymin>18</ymin>
			<xmax>492</xmax>
			<ymax>147</ymax>
		</bndbox>
	</object>
	<object>
		<name>storage tank</name>
		<pose>overlook</pose>
		<truncated>0</truncated>
		<difficult>0</difficult>
		<bndbox>
			<xmin>466</xmin>
			<ymin>150</ymin>
			<xmax>618</xmax>
			<ymax>292</ymax>
		</bndbox>
	</object>
	<object>
		<name>storage tank</name>
		<pose>overlook</pose>
		<truncated>0</truncated>
		<difficult>0</difficult>
		<bndbox>
			<xmin>590</xmin>
			<ymin>274</ymin>
			<xmax>745</xmax>
			<ymax>426</ymax>
		</bndbox>
	</object>
	<object>
		<name>storage tank</name>
		<pose>overlook</pose>
		<truncated>0</truncated>
		<difficult>0</difficult>
		<bndbox>
			<xmin>393</xmin>
			<ymin>308</ymin>
			<xmax>539</xmax>
			<ymax>440</ymax>
		</bndbox>
	</object>
	<object>
		<name>storage tank</name>
		<pose>overlook</pose>
		<truncated>0</truncated>
		<difficult>0</difficult>
		<bndbox>
			<xmin>504</xmin>
			<ymin>425</ymin>
			<xmax>648</xmax>
			<ymax>554</ymax>
		</bndbox>
	</object>
	<object>
		<name>storage tank</name>
		<pose>overlook</pose>
		<truncated>0</truncated>
		<difficult>0</difficult>
		<bndbox>
			<xmin>280</xmin>
			<ymin>415</ymin>
			<xmax>422</xmax>
			<ymax>545</ymax>
		</bndbox>
	</object>
	<object>
		<name>storage tank</name>
		<pose>overlook</pose>
		<truncated>0</truncated>
		<difficult>0</difficult>
		<bndbox>
			<xmin>384</xmin>
			<ymin>535</ymin>
			<xmax>524</xmax>
			<ymax>660</ymax>
		</bndbox>
	</object>
	<object>
		<name>storage tank</name>
		<pose>overlook</pose>
		<truncated>0</truncated>
		<difficult>0</difficult>
		<bndbox>
			<xmin>115</xmin>
			<ymin>230</ymin>
			<xmax>256</xmax>
			<ymax>359</ymax>
		</bndbox>
	</object>
	<object>
		<name>storage tank</name>
		<pose>overlook</pose>
		<truncated>0</truncated>
		<difficult>0</difficult>
		<bndbox>
			<xmin>233</xmin>
			<ymin>123</ymin>
			<xmax>373</xmax>
			<ymax>254</ymax>
		</bndbox>
	</object>
	<object>
		<name>storage tank</name>
		<pose>overlook</pose>
		<truncated>0</truncated>
		<difficult>0</difficult>
		<bndbox>
			<xmin>13</xmin>
			<ymin>108</ymin>
			<xmax>145</xmax>
			<ymax>242</ymax>
		</bndbox>
	</object>
	<object>
		<name>storage tank</name>
		<pose>overlook</pose>
		<truncated>0</truncated>
		<difficult>0</difficult>
		<bndbox>
			<xmin>509</xmin>
			<ymin>4</ymin>
			<xmax>604</xmax>
			<ymax>86</ymax>
		</bndbox>
	</object>
</annotation>
