<annotation>
	<folder>OPTIMAL_Z</folder>
	<filename>04031.jpg</filename>
	<source>
		<database>The OPTIMAL_Z Database</database>
		<annotation>OPTIMAL_Z_anno</annotation>
		<image>OPTIMAL_Z_img</image>
		<flickrid>NULL</flickrid>
	</source>
	<owner>
		<flickrid>NULL</flickrid>
		<name>snail_crowling</name>
	</owner>
	<size>
		<width>2010</width>
		<height>1493</height>
		<depth>3</depth>
	</size>
	<segmented>0</segmented>
	<object>
		<name>parking lot</name>
		<pose>overlook</pose>
		<truncated>0</truncated>
		<difficult>0</difficult>
		<bndbox>
			<xmin>2</xmin>
			<ymin>801</ymin>
			<xmax>243</xmax>
			<ymax>1124</ymax>
		</bndbox>
	</object>
	<object>
		<name>parking lot</name>
		<pose>overlook</pose>
		<truncated>0</truncated>
		<difficult>0</difficult>
		<bndbox>
			<xmin>353</xmin>
			<ymin>1205</ymin>
			<xmax>443</xmax>
			<ymax>1331</ymax>
		</bndbox>
	</object>
	<object>
		<name>parking lot</name>
		<pose>overlook</pose>
		<truncated>0</truncated>
		<difficult>0</difficult>
		<bndbox>
			<xmin>797</xmin>
			<ymin>1359</ymin>
			<xmax>885</xmax>
			<ymax>1490</ymax>
		</bndbox>
	</object>
	<object>
		<name>parking lot</name>
		<pose>overlook</pose>
		<truncated>0</truncated>
		<difficult>0</difficult>
		<bndbox>
			<xmin>1412</xmin>
			<ymin>1101</ymin>
			<xmax>1615</xmax>
			<ymax>1295</ymax>
		</bndbox>
	</object>
	<object>
		<name>parking lot</name>
		<pose>overlook</pose>
		<truncated>0</truncated>
		<difficult>0</difficult>
		<bndbox>
			<xmin>1748</xmin>
			<ymin>594</ymin>
			<xmax>2009</xmax>
			<ymax>855</ymax>
		</bndbox>
	</object>
	<object>
		<name>parking lot</name>
		<pose>overlook</pose>
		<truncated>0</truncated>
		<difficult>0</difficult>
		<bndbox>
			<xmin>1733</xmin>
			<ymin>289</ymin>
			<xmax>1844</xmax>
			<ymax>397</ymax>
		</bndbox>
	</object>
	<object>
		<name>parking lot</name>
		<pose>overlook</pose>
		<truncated>0</truncated>
		<difficult>0</difficult>
		<bndbox>
			<xmin>1019</xmin>
			<ymin>7</ymin>
			<xmax>1237</xmax>
			<ymax>215</ymax>
		</bndbox>
	</object>
	<object>
		<name>parking lot</name>
		<pose>overlook</pose>
		<truncated>0</truncated>
		<difficult>0</difficult>
		<bndbox>
			<xmin>855</xmin>
			<ymin>2</ymin>
			<xmax>927</xmax>
			<ymax>73</ymax>
		</bndbox>
	</object>
	<object>
		<name>parking lot</name>
		<pose>overlook</pose>
		<truncated>0</truncated>
		<difficult>0</difficult>
		<bndbox>
			<xmin>1035</xmin>
			<ymin>767</ymin>
			<xmax>1353</xmax>
			<ymax>1033</ymax>
		</bndbox>
	</object>
	<object>
		<name>crossroad</name>
		<pose>overlook</pose>
		<truncated>0</truncated>
		<difficult>0</difficult>
		<bndbox>
			<xmin>59</xmin>
			<ymin>455</ymin>
			<xmax>542</xmax>
			<ymax>965</ymax>
		</bndbox>
	</object>
	<object>
		<name>crossroad</name>
		<pose>overlook</pose>
		<truncated>0</truncated>
		<difficult>0</difficult>
		<bndbox>
			<xmin>428</xmin>
			<ymin>692</ymin>
			<xmax>839</xmax>
			<ymax>1148</ymax>
		</bndbox>
	</object>
	<object>
		<name>crossroad</name>
		<pose>overlook</pose>
		<truncated>0</truncated>
		<difficult>0</difficult>
		<bndbox>
			<xmin>734</xmin>
			<ymin>866</ymin>
			<xmax>1250</xmax>
			<ymax>1397</ymax>
		</bndbox>
	</object>
	<object>
		<name>crossroad</name>
		<pose>overlook</pose>
		<truncated>0</truncated>
		<difficult>0</difficult>
		<bndbox>
			<xmin>1238</xmin>
			<ymin>506</ymin>
			<xmax>1655</xmax>
			<ymax>932</ymax>
		</bndbox>
	</object>
	<object>
		<name>crossroad</name>
		<pose>overlook</pose>
		<truncated>0</truncated>
		<difficult>0</difficult>
		<bndbox>
			<xmin>830</xmin>
			<ymin>230</ymin>
			<xmax>1283</xmax>
			<ymax>692</ymax>
		</bndbox>
	</object>
	<object>
		<name>T junction</name>
		<pose>overlook</pose>
		<truncated>0</truncated>
		<difficult>0</difficult>
		<bndbox>
			<xmin>512</xmin>
			<ymin>68</ymin>
			<xmax>908</xmax>
			<ymax>473</ymax>
		</bndbox>
	</object>
</annotation>
