<annotation>
	<folder>OPTIMAL_Z</folder>
	<filename>04252.jpg</filename>
	<source>
		<database>The OPTIMAL_Z Database</database>
		<annotation>OPTIMAL_Z_anno</annotation>
		<image>OPTIMAL_Z_img</image>
		<flickrid>NULL</flickrid>
	</source>
	<owner>
		<flickrid>NULL</flickrid>
		<name>snail_crowling</name>
	</owner>
	<size>
		<width>1080</width>
		<height>1585</height>
		<depth>3</depth>
	</size>
	<segmented>0</segmented>
	<object>
		<name>parking lot</name>
		<pose>overlook</pose>
		<truncated>0</truncated>
		<difficult>0</difficult>
		<bndbox>
			<xmin>59</xmin>
			<ymin>904</ymin>
			<xmax>222</xmax>
			<ymax>1021</ymax>
		</bndbox>
	</object>
	<object>
		<name>parking lot</name>
		<pose>overlook</pose>
		<truncated>0</truncated>
		<difficult>0</difficult>
		<bndbox>
			<xmin>5</xmin>
			<ymin>942</ymin>
			<xmax>120</xmax>
			<ymax>1050</ymax>
		</bndbox>
	</object>
	<object>
		<name>parking lot</name>
		<pose>overlook</pose>
		<truncated>0</truncated>
		<difficult>0</difficult>
		<bndbox>
			<xmin>344</xmin>
			<ymin>692</ymin>
			<xmax>583</xmax>
			<ymax>992</ymax>
		</bndbox>
	</object>
	<object>
		<name>parking lot</name>
		<pose>overlook</pose>
		<truncated>0</truncated>
		<difficult>0</difficult>
		<bndbox>
			<xmin>840</xmin>
			<ymin>156</ymin>
			<xmax>976</xmax>
			<ymax>286</ymax>
		</bndbox>
	</object>
	<object>
		<name>parking lot</name>
		<pose>overlook</pose>
		<truncated>0</truncated>
		<difficult>0</difficult>
		<bndbox>
			<xmin>885</xmin>
			<ymin>64</ymin>
			<xmax>1025</xmax>
			<ymax>155</ymax>
		</bndbox>
	</object>
	<object>
		<name>harbor</name>
		<pose>overlook</pose>
		<truncated>0</truncated>
		<difficult>0</difficult>
		<bndbox>
			<xmin>362</xmin>
			<ymin>797</ymin>
			<xmax>667</xmax>
			<ymax>1126</ymax>
		</bndbox>
	</object>
	<object>
		<name>harbor</name>
		<pose>overlook</pose>
		<truncated>0</truncated>
		<difficult>0</difficult>
		<bndbox>
			<xmin>7</xmin>
			<ymin>1232</ymin>
			<xmax>315</xmax>
			<ymax>1561</ymax>
		</bndbox>
	</object>
	<object>
		<name>harbor</name>
		<pose>overlook</pose>
		<truncated>0</truncated>
		<difficult>0</difficult>
		<bndbox>
			<xmin>239</xmin>
			<ymin>1173</ymin>
			<xmax>548</xmax>
			<ymax>1542</ymax>
		</bndbox>
	</object>
</annotation>
