<annotation>
	<folder>OPTIMAL_Z</folder>
	<filename>05681.jpg</filename>
	<source>
		<database>The OPTIMAL_Z Database</database>
		<annotation>OPTIMAL_Z_anno</annotation>
		<image>OPTIMAL_Z_img</image>
		<flickrid>NULL</flickrid>
	</source>
	<owner>
		<flickrid>NULL</flickrid>
		<name>snail_crowling</name>
	</owner>
	<size>
		<width>1068</width>
		<height>810</height>
		<depth>3</depth>
	</size>
	<segmented>0</segmented>
	<object>
		<name>ground track field</name>
		<pose>overlook</pose>
		<truncated>0</truncated>
		<difficult>0</difficult>
		<bndbox>
			<xmin>196</xmin>
			<ymin>412</ymin>
			<xmax>532</xmax>
			<ymax>600</ymax>
		</bndbox>
	</object>
	<object>
		<name>basketball court</name>
		<pose>overlook</pose>
		<truncated>0</truncated>
		<difficult>0</difficult>
		<bndbox>
			<xmin>702</xmin>
			<ymin>445</ymin>
			<xmax>775</xmax>
			<ymax>565</ymax>
		</bndbox>
	</object>
	<object>
		<name>basketball court</name>
		<pose>overlook</pose>
		<truncated>0</truncated>
		<difficult>0</difficult>
		<bndbox>
			<xmin>777</xmin>
			<ymin>445</ymin>
			<xmax>841</xmax>
			<ymax>567</ymax>
		</bndbox>
	</object>
</annotation>
