<annotation>
	<folder>OPTIMAL_Z</folder>
	<filename>08646.jpg</filename>
	<source>
		<database>The OPTIMAL_Z Database</database>
		<annotation>OPTIMAL_Z_anno</annotation>
		<image>OPTIMAL_Z_img</image>
		<flickrid>NULL</flickrid>
	</source>
	<owner>
		<flickrid>NULL</flickrid>
		<name>snail_crowling</name>
	</owner>
	<size>
		<width>772</width>
		<height>860</height>
		<depth>3</depth>
	</size>
	<segmented>0</segmented>
	<object>
		<name>crossroad</name>
		<pose>overlook</pose>
		<truncated>0</truncated>
		<difficult>0</difficult>
		<bndbox>
			<xmin>169</xmin>
			<ymin>228</ymin>
			<xmax>588</xmax>
			<ymax>634</ymax>
		</bndbox>
	</object>
	<object>
		<name>T junction</name>
		<pose>overlook</pose>
		<truncated>0</truncated>
		<difficult>0</difficult>
		<bndbox>
			<xmin>435</xmin>
			<ymin>440</ymin>
			<xmax>699</xmax>
			<ymax>718</ymax>
		</bndbox>
	</object>
</annotation>
