<annotation>
	<folder>OPTIMAL_Z</folder>
	<filename>09350.jpg</filename>
	<source>
		<database>The OPTIMAL_Z Database</database>
		<annotation>OPTIMAL_Z_anno</annotation>
		<image>OPTIMAL_Z_img</image>
		<flickrid>NULL</flickrid>
	</source>
	<owner>
		<flickrid>NULL</flickrid>
		<name>snail_crowling</name>
	</owner>
	<size>
		<width>665</width>
		<height>723</height>
		<depth>3</depth>
	</size>
	<segmented>0</segmented>
	<object>
		<name>parking lot</name>
		<pose>overlook</pose>
		<truncated>0</truncated>
		<difficult>0</difficult>
		<bndbox>
			<xmin>319</xmin>
			<ymin>262</ymin>
			<xmax>419</xmax>
			<ymax>508</ymax>
		</bndbox>
	</object>
	<object>
		<name>T junction</name>
		<pose>overlook</pose>
		<truncated>0</truncated>
		<difficult>0</difficult>
		<bndbox>
			<xmin>296</xmin>
			<ymin>255</ymin>
			<xmax>551</xmax>
			<ymax>507</ymax>
		</bndbox>
	</object>
	<object>
		<name>T junction</name>
		<pose>overlook</pose>
		<truncated>0</truncated>
		<difficult>0</difficult>
		<bndbox>
			<xmin>297</xmin>
			<ymin>401</ymin>
			<xmax>563</xmax>
			<ymax>647</ymax>
		</bndbox>
	</object>
</annotation>
