<annotation>
	<folder>OPTIMAL_Z</folder>
	<filename>11042.jpg</filename>
	<source>
		<database>The OPTIMAL_Z Database</database>
		<annotation>OPTIMAL_Z_anno</annotation>
		<image>OPTIMAL_Z_img</image>
		<flickrid>NULL</flickrid>
	</source>
	<owner>
		<flickrid>NULL</flickrid>
		<name>snail_crowling</name>
	</owner>
	<size>
		<width>688</width>
		<height>1014</height>
		<depth>3</depth>
	</size>
	<segmented>0</segmented>
	<object>
		<name>vehicle</name>
		<pose>overlook</pose>
		<truncated>0</truncated>
		<difficult>0</difficult>
		<bndbox>
			<xmin>543</xmin>
			<ymin>89</ymin>
			<xmax>584</xmax>
			<ymax>139</ymax>
		</bndbox>
	</object>
	<object>
		<name>vehicle</name>
		<pose>overlook</pose>
		<truncated>0</truncated>
		<difficult>0</difficult>
		<bndbox>
			<xmin>275</xmin>
			<ymin>552</ymin>
			<xmax>310</xmax>
			<ymax>602</ymax>
		</bndbox>
	</object>
	<object>
		<name>vehicle</name>
		<pose>overlook</pose>
		<truncated>0</truncated>
		<difficult>0</difficult>
		<bndbox>
			<xmin>246</xmin>
			<ymin>597</ymin>
			<xmax>284</xmax>
			<ymax>646</ymax>
		</bndbox>
	</object>
	<object>
		<name>vehicle</name>
		<pose>overlook</pose>
		<truncated>0</truncated>
		<difficult>0</difficult>
		<bndbox>
			<xmin>191</xmin>
			<ymin>691</ymin>
			<xmax>228</xmax>
			<ymax>741</ymax>
		</bndbox>
	</object>
	<object>
		<name>vehicle</name>
		<pose>overlook</pose>
		<truncated>0</truncated>
		<difficult>0</difficult>
		<bndbox>
			<xmin>101</xmin>
			<ymin>799</ymin>
			<xmax>134</xmax>
			<ymax>853</ymax>
		</bndbox>
	</object>
	<object>
		<name>vehicle</name>
		<pose>overlook</pose>
		<truncated>0</truncated>
		<difficult>0</difficult>
		<bndbox>
			<xmin>327</xmin>
			<ymin>680</ymin>
			<xmax>373</xmax>
			<ymax>717</ymax>
		</bndbox>
	</object>
	<object>
		<name>vehicle</name>
		<pose>overlook</pose>
		<truncated>0</truncated>
		<difficult>0</difficult>
		<bndbox>
			<xmin>287</xmin>
			<ymin>747</ymin>
			<xmax>324</xmax>
			<ymax>800</ymax>
		</bndbox>
	</object>
	<object>
		<name>vehicle</name>
		<pose>overlook</pose>
		<truncated>0</truncated>
		<difficult>0</difficult>
		<bndbox>
			<xmin>260</xmin>
			<ymin>802</ymin>
			<xmax>294</xmax>
			<ymax>849</ymax>
		</bndbox>
	</object>
</annotation>
