<annotation>
	<folder>OPTIMAL_Z</folder>
	<filename>13052.jpg</filename>
	<source>
		<database>The OPTIMAL_Z Database</database>
		<annotation>OPTIMAL_Z_anno</annotation>
		<image>OPTIMAL_Z_img</image>
		<flickrid>NULL</flickrid>
	</source>
	<owner>
		<flickrid>NULL</flickrid>
		<name>snail_crowling</name>
	</owner>
	<size>
		<width>1042</width>
		<height>998</height>
		<depth>3</depth>
	</size>
	<segmented>0</segmented>
	<object>
		<name>parking lot</name>
		<pose>overlook</pose>
		<truncated>0</truncated>
		<difficult>0</difficult>
		<bndbox>
			<xmin>216</xmin>
			<ymin>288</ymin>
			<xmax>345</xmax>
			<ymax>515</ymax>
		</bndbox>
	</object>
	<object>
		<name>parking lot</name>
		<pose>overlook</pose>
		<truncated>0</truncated>
		<difficult>0</difficult>
		<bndbox>
			<xmin>84</xmin>
			<ymin>27</ymin>
			<xmax>166</xmax>
			<ymax>180</ymax>
		</bndbox>
	</object>
	<object>
		<name>parking lot</name>
		<pose>overlook</pose>
		<truncated>0</truncated>
		<difficult>0</difficult>
		<bndbox>
			<xmin>13</xmin>
			<ymin>583</ymin>
			<xmax>156</xmax>
			<ymax>836</ymax>
		</bndbox>
	</object>
	<object>
		<name>parking lot</name>
		<pose>overlook</pose>
		<truncated>0</truncated>
		<difficult>0</difficult>
		<bndbox>
			<xmin>246</xmin>
			<ymin>568</ymin>
			<xmax>375</xmax>
			<ymax>649</ymax>
		</bndbox>
	</object>
	<object>
		<name>parking lot</name>
		<pose>overlook</pose>
		<truncated>0</truncated>
		<difficult>0</difficult>
		<bndbox>
			<xmin>549</xmin>
			<ymin>249</ymin>
			<xmax>653</xmax>
			<ymax>420</ymax>
		</bndbox>
	</object>
	<object>
		<name>parking lot</name>
		<pose>overlook</pose>
		<truncated>0</truncated>
		<difficult>0</difficult>
		<bndbox>
			<xmin>415</xmin>
			<ymin>6</ymin>
			<xmax>537</xmax>
			<ymax>203</ymax>
		</bndbox>
	</object>
	<object>
		<name>crossroad</name>
		<pose>overlook</pose>
		<truncated>0</truncated>
		<difficult>0</difficult>
		<bndbox>
			<xmin>229</xmin>
			<ymin>428</ymin>
			<xmax>641</xmax>
			<ymax>829</ymax>
		</bndbox>
	</object>
	<object>
		<name>T junction</name>
		<pose>overlook</pose>
		<truncated>0</truncated>
		<difficult>0</difficult>
		<bndbox>
			<xmin>590</xmin>
			<ymin>506</ymin>
			<xmax>992</xmax>
			<ymax>944</ymax>
		</bndbox>
	</object>
</annotation>
