<annotation>
	<folder>OPTIMAL_Z</folder>
	<filename>13976.jpg</filename>
	<source>
		<database>The OPTIMAL_Z Database</database>
		<annotation>OPTIMAL_Z_anno</annotation>
		<image>OPTIMAL_Z_img</image>
		<flickrid>NULL</flickrid>
	</source>
	<owner>
		<flickrid>NULL</flickrid>
		<name>snail_crowling</name>
	</owner>
	<size>
		<width>1580</width>
		<height>1172</height>
		<depth>3</depth>
	</size>
	<segmented>0</segmented>
	<object>
		<name>ground track field</name>
		<pose>overlook</pose>
		<truncated>0</truncated>
		<difficult>0</difficult>
		<bndbox>
			<xmin>1029</xmin>
			<ymin>5</ymin>
			<xmax>1329</xmax>
			<ymax>407</ymax>
		</bndbox>
	</object>
	<object>
		<name>basketball court</name>
		<pose>overlook</pose>
		<truncated>0</truncated>
		<difficult>0</difficult>
		<bndbox>
			<xmin>929</xmin>
			<ymin>185</ymin>
			<xmax>1017</xmax>
			<ymax>323</ymax>
		</bndbox>
	</object>
	<object>
		<name>basketball court</name>
		<pose>overlook</pose>
		<truncated>0</truncated>
		<difficult>0</difficult>
		<bndbox>
			<xmin>927</xmin>
			<ymin>35</ymin>
			<xmax>1015</xmax>
			<ymax>173</ymax>
		</bndbox>
	</object>
</annotation>
