<annotation>
	<folder>OPTIMAL_Z</folder>
	<filename>14738.jpg</filename>
	<source>
		<database>The OPTIMAL_Z Database</database>
		<annotation>OPTIMAL_Z_anno</annotation>
		<image>OPTIMAL_Z_img</image>
		<flickrid>NULL</flickrid>
	</source>
	<owner>
		<flickrid>NULL</flickrid>
		<name>snail_crowling</name>
	</owner>
	<size>
		<width>950</width>
		<height>570</height>
		<depth>3</depth>
	</size>
	<segmented>0</segmented>
	<object>
		<name>harbor</name>
		<pose>overlook</pose>
		<truncated>0</truncated>
		<difficult>0</difficult>
		<bndbox>
			<xmin>469</xmin>
			<ymin>442</ymin>
			<xmax>602</xmax>
			<ymax>506</ymax>
		</bndbox>
	</object>
	<object>
		<name>harbor</name>
		<pose>overlook</pose>
		<truncated>0</truncated>
		<difficult>0</difficult>
		<bndbox>
			<xmin>448</xmin>
			<ymin>360</ymin>
			<xmax>613</xmax>
			<ymax>421</ymax>
		</bndbox>
	</object>
	<object>
		<name>harbor</name>
		<pose>overlook</pose>
		<truncated>0</truncated>
		<difficult>0</difficult>
		<bndbox>
			<xmin>431</xmin>
			<ymin>306</ymin>
			<xmax>608</xmax>
			<ymax>370</ymax>
		</bndbox>
	</object>
	<object>
		<name>harbor</name>
		<pose>overlook</pose>
		<truncated>0</truncated>
		<difficult>0</difficult>
		<bndbox>
			<xmin>410</xmin>
			<ymin>248</ymin>
			<xmax>602</xmax>
			<ymax>306</ymax>
		</bndbox>
	</object>
	<object>
		<name>harbor</name>
		<pose>overlook</pose>
		<truncated>0</truncated>
		<difficult>0</difficult>
		<bndbox>
			<xmin>413</xmin>
			<ymin>177</ymin>
			<xmax>595</xmax>
			<ymax>249</ymax>
		</bndbox>
	</object>
	<object>
		<name>harbor</name>
		<pose>overlook</pose>
		<truncated>0</truncated>
		<difficult>0</difficult>
		<bndbox>
			<xmin>386</xmin>
			<ymin>96</ymin>
			<xmax>562</xmax>
			<ymax>173</ymax>
		</bndbox>
	</object>
</annotation>
