<annotation>
	<folder>OPTIMAL_Z</folder>
	<filename>16835.jpg</filename>
	<source>
		<database>The OPTIMAL_Z Database</database>
		<annotation>OPTIMAL_Z_anno</annotation>
		<image>OPTIMAL_Z_img</image>
		<flickrid>NULL</flickrid>
	</source>
	<owner>
		<flickrid>NULL</flickrid>
		<name>snail_crowling</name>
	</owner>
	<size>
		<width>800</width>
		<height>868</height>
		<depth>3</depth>
	</size>
	<segmented>0</segmented>
	<object>
		<name>crossroad</name>
		<pose>overlook</pose>
		<truncated>0</truncated>
		<difficult>0</difficult>
		<bndbox>
			<xmin>374</xmin>
			<ymin>280</ymin>
			<xmax>641</xmax>
			<ymax>541</ymax>
		</bndbox>
	</object>
	<object>
		<name>T junction</name>
		<pose>overlook</pose>
		<truncated>0</truncated>
		<difficult>0</difficult>
		<bndbox>
			<xmin>409</xmin>
			<ymin>529</ymin>
			<xmax>667</xmax>
			<ymax>780</ymax>
		</bndbox>
	</object>
	<object>
		<name>T junction</name>
		<pose>overlook</pose>
		<truncated>0</truncated>
		<difficult>0</difficult>
		<bndbox>
			<xmin>288</xmin>
			<ymin>37</ymin>
			<xmax>568</xmax>
			<ymax>323</ymax>
		</bndbox>
	</object>
</annotation>
