<annotation>
	<folder>OPTIMAL_Z</folder>
	<filename>17714.jpg</filename>
	<source>
		<database>The OPTIMAL_Z Database</database>
		<annotation>OPTIMAL_Z_anno</annotation>
		<image>OPTIMAL_Z_img</image>
		<flickrid>NULL</flickrid>
	</source>
	<owner>
		<flickrid>NULL</flickrid>
		<name>snail_crowling</name>
	</owner>
	<size>
		<width>547</width>
		<height>1266</height>
		<depth>3</depth>
	</size>
	<segmented>0</segmented>
	<object>
		<name>bridge</name>
		<pose>overlook</pose>
		<truncated>0</truncated>
		<difficult>0</difficult>
		<bndbox>
			<xmin>269</xmin>
			<ymin>38</ymin>
			<xmax>352</xmax>
			<ymax>127</ymax>
		</bndbox>
	</object>
	<object>
		<name>bridge</name>
		<pose>overlook</pose>
		<truncated>0</truncated>
		<difficult>0</difficult>
		<bndbox>
			<xmin>424</xmin>
			<ymin>444</ymin>
			<xmax>495</xmax>
			<ymax>546</ymax>
		</bndbox>
	</object>
	<object>
		<name>bridge</name>
		<pose>overlook</pose>
		<truncated>0</truncated>
		<difficult>0</difficult>
		<bndbox>
			<xmin>189</xmin>
			<ymin>968</ymin>
			<xmax>284</xmax>
			<ymax>1048</ymax>
		</bndbox>
	</object>
	<object>
		<name>bridge</name>
		<pose>overlook</pose>
		<truncated>0</truncated>
		<difficult>0</difficult>
		<bndbox>
			<xmin>218</xmin>
			<ymin>1103</ymin>
			<xmax>287</xmax>
			<ymax>1168</ymax>
		</bndbox>
	</object>
	<object>
		<name>bridge</name>
		<pose>overlook</pose>
		<truncated>0</truncated>
		<difficult>0</difficult>
		<bndbox>
			<xmin>269</xmin>
			<ymin>1164</ymin>
			<xmax>353</xmax>
			<ymax>1237</ymax>
		</bndbox>
	</object>
</annotation>
