<annotation>
	<folder>OPTIMAL_Z</folder>
	<filename>17768.jpg</filename>
	<source>
		<database>The OPTIMAL_Z Database</database>
		<annotation>OPTIMAL_Z_anno</annotation>
		<image>OPTIMAL_Z_img</image>
		<flickrid>NULL</flickrid>
	</source>
	<owner>
		<flickrid>NULL</flickrid>
		<name>snail_crowling</name>
	</owner>
	<size>
		<width>556</width>
		<height>918</height>
		<depth>3</depth>
	</size>
	<segmented>0</segmented>
	<object>
		<name>baseball diamond</name>
		<pose>overlook</pose>
		<truncated>0</truncated>
		<difficult>0</difficult>
		<bndbox>
			<xmin>425</xmin>
			<ymin>222</ymin>
			<xmax>479</xmax>
			<ymax>286</ymax>
		</bndbox>
	</object>
	<object>
		<name>baseball diamond</name>
		<pose>overlook</pose>
		<truncated>0</truncated>
		<difficult>0</difficult>
		<bndbox>
			<xmin>319</xmin>
			<ymin>455</ymin>
			<xmax>381</xmax>
			<ymax>531</ymax>
		</bndbox>
	</object>
	<object>
		<name>baseball diamond</name>
		<pose>overlook</pose>
		<truncated>0</truncated>
		<difficult>0</difficult>
		<bndbox>
			<xmin>331</xmin>
			<ymin>557</ymin>
			<xmax>421</xmax>
			<ymax>663</ymax>
		</bndbox>
	</object>
	<object>
		<name>baseball diamond</name>
		<pose>overlook</pose>
		<truncated>0</truncated>
		<difficult>0</difficult>
		<bndbox>
			<xmin>242</xmin>
			<ymin>580</ymin>
			<xmax>306</xmax>
			<ymax>656</ymax>
		</bndbox>
	</object>
	<object>
		<name>baseball diamond</name>
		<pose>overlook</pose>
		<truncated>0</truncated>
		<difficult>0</difficult>
		<bndbox>
			<xmin>222</xmin>
			<ymin>476</ymin>
			<xmax>289</xmax>
			<ymax>549</ymax>
		</bndbox>
	</object>
	<object>
		<name>baseball diamond</name>
		<pose>overlook</pose>
		<truncated>0</truncated>
		<difficult>0</difficult>
		<bndbox>
			<xmin>280</xmin>
			<ymin>233</ymin>
			<xmax>347</xmax>
			<ymax>314</ymax>
		</bndbox>
	</object>
	<object>
		<name>baseball diamond</name>
		<pose>overlook</pose>
		<truncated>0</truncated>
		<difficult>0</difficult>
		<bndbox>
			<xmin>133</xmin>
			<ymin>240</ymin>
			<xmax>242</xmax>
			<ymax>364</ymax>
		</bndbox>
	</object>
	<object>
		<name>baseball diamond</name>
		<pose>overlook</pose>
		<truncated>0</truncated>
		<difficult>0</difficult>
		<bndbox>
			<xmin>124</xmin>
			<ymin>627</ymin>
			<xmax>180</xmax>
			<ymax>683</ymax>
		</bndbox>
	</object>
</annotation>
