<annotation>
	<folder>OPTIMAL_Z</folder>
	<filename>18071.jpg</filename>
	<source>
		<database>The OPTIMAL_Z Database</database>
		<annotation>OPTIMAL_Z_anno</annotation>
		<image>OPTIMAL_Z_img</image>
		<flickrid>NULL</flickrid>
	</source>
	<owner>
		<flickrid>NULL</flickrid>
		<name>snail_crowling</name>
	</owner>
	<size>
		<width>598</width>
		<height>778</height>
		<depth>3</depth>
	</size>
	<segmented>0</segmented>
	<object>
		<name>bridge</name>
		<pose>overlook</pose>
		<truncated>0</truncated>
		<difficult>0</difficult>
		<bndbox>
			<xmin>95</xmin>
			<ymin>323</ymin>
			<xmax>235</xmax>
			<ymax>572</ymax>
		</bndbox>
	</object>
	<object>
		<name>bridge</name>
		<pose>overlook</pose>
		<truncated>0</truncated>
		<difficult>0</difficult>
		<bndbox>
			<xmin>312</xmin>
			<ymin>143</ymin>
			<xmax>501</xmax>
			<ymax>376</ymax>
		</bndbox>
	</object>
</annotation>
