<annotation>
	<folder>OPTIMAL_Z</folder>
	<filename>19561.jpg</filename>
	<source>
		<database>The OPTIMAL_Z Database</database>
		<annotation>OPTIMAL_Z_anno</annotation>
		<image>OPTIMAL_Z_img</image>
		<flickrid>NULL</flickrid>
	</source>
	<owner>
		<flickrid>NULL</flickrid>
		<name>snail_crowling</name>
	</owner>
	<size>
		<width>1367</width>
		<height>959</height>
		<depth>3</depth>
	</size>
	<segmented>0</segmented>
	<object>
		<name>bridge</name>
		<pose>overlook</pose>
		<truncated>0</truncated>
		<difficult>0</difficult>
		<bndbox>
			<xmin>125</xmin>
			<ymin>227</ymin>
			<xmax>321</xmax>
			<ymax>643</ymax>
		</bndbox>
	</object>
	<object>
		<name>bridge</name>
		<pose>overlook</pose>
		<truncated>0</truncated>
		<difficult>0</difficult>
		<bndbox>
			<xmin>925</xmin>
			<ymin>386</ymin>
			<xmax>1126</xmax>
			<ymax>725</ymax>
		</bndbox>
	</object>
	<object>
		<name>bridge</name>
		<pose>overlook</pose>
		<truncated>0</truncated>
		<difficult>0</difficult>
		<bndbox>
			<xmin>537</xmin>
			<ymin>303</ymin>
			<xmax>983</xmax>
			<ymax>697</ymax>
		</bndbox>
	</object>
</annotation>
