<annotation>
	<folder>OPTIMAL_Z</folder>
	<filename>20994.jpg</filename>
	<source>
		<database>The OPTIMAL_Z Database</database>
		<annotation>OPTIMAL_Z_anno</annotation>
		<image>OPTIMAL_Z_img</image>
		<flickrid>NULL</flickrid>
	</source>
	<owner>
		<flickrid>NULL</flickrid>
		<name>snail_crowling</name>
	</owner>
	<size>
		<width>529</width>
		<height>618</height>
		<depth>3</depth>
	</size>
	<segmented>0</segmented>
	<object>
		<name>vehicle</name>
		<pose>overlook</pose>
		<truncated>0</truncated>
		<difficult>0</difficult>
		<bndbox>
			<xmin>65</xmin>
			<ymin>2</ymin>
			<xmax>111</xmax>
			<ymax>34</ymax>
		</bndbox>
	</object>
	<object>
		<name>vehicle</name>
		<pose>overlook</pose>
		<truncated>0</truncated>
		<difficult>0</difficult>
		<bndbox>
			<xmin>53</xmin>
			<ymin>31</ymin>
			<xmax>99</xmax>
			<ymax>62</ymax>
		</bndbox>
	</object>
	<object>
		<name>vehicle</name>
		<pose>overlook</pose>
		<truncated>0</truncated>
		<difficult>0</difficult>
		<bndbox>
			<xmin>44</xmin>
			<ymin>56</ymin>
			<xmax>90</xmax>
			<ymax>86</ymax>
		</bndbox>
	</object>
	<object>
		<name>vehicle</name>
		<pose>overlook</pose>
		<truncated>0</truncated>
		<difficult>0</difficult>
		<bndbox>
			<xmin>39</xmin>
			<ymin>77</ymin>
			<xmax>84</xmax>
			<ymax>110</ymax>
		</bndbox>
	</object>
	<object>
		<name>vehicle</name>
		<pose>overlook</pose>
		<truncated>0</truncated>
		<difficult>0</difficult>
		<bndbox>
			<xmin>31</xmin>
			<ymin>105</ymin>
			<xmax>77</xmax>
			<ymax>136</ymax>
		</bndbox>
	</object>
	<object>
		<name>vehicle</name>
		<pose>overlook</pose>
		<truncated>0</truncated>
		<difficult>0</difficult>
		<bndbox>
			<xmin>221</xmin>
			<ymin>74</ymin>
			<xmax>252</xmax>
			<ymax>123</ymax>
		</bndbox>
	</object>
	<object>
		<name>vehicle</name>
		<pose>overlook</pose>
		<truncated>0</truncated>
		<difficult>0</difficult>
		<bndbox>
			<xmin>225</xmin>
			<ymin>157</ymin>
			<xmax>259</xmax>
			<ymax>215</ymax>
		</bndbox>
	</object>
	<object>
		<name>vehicle</name>
		<pose>overlook</pose>
		<truncated>0</truncated>
		<difficult>0</difficult>
		<bndbox>
			<xmin>158</xmin>
			<ymin>379</ymin>
			<xmax>179</xmax>
			<ymax>435</ymax>
		</bndbox>
	</object>
</annotation>
