<annotation>
	<folder>OPTIMAL_Z</folder>
	<filename>21005.jpg</filename>
	<source>
		<database>The OPTIMAL_Z Database</database>
		<annotation>OPTIMAL_Z_anno</annotation>
		<image>OPTIMAL_Z_img</image>
		<flickrid>NULL</flickrid>
	</source>
	<owner>
		<flickrid>NULL</flickrid>
		<name>snail_crowling</name>
	</owner>
	<size>
		<width>676</width>
		<height>969</height>
		<depth>3</depth>
	</size>
	<segmented>0</segmented>
	<object>
		<name>vehicle</name>
		<pose>overlook</pose>
		<truncated>0</truncated>
		<difficult>0</difficult>
		<bndbox>
			<xmin>224</xmin>
			<ymin>293</ymin>
			<xmax>265</xmax>
			<ymax>343</ymax>
		</bndbox>
	</object>
	<object>
		<name>vehicle</name>
		<pose>overlook</pose>
		<truncated>0</truncated>
		<difficult>0</difficult>
		<bndbox>
			<xmin>312</xmin>
			<ymin>440</ymin>
			<xmax>352</xmax>
			<ymax>489</ymax>
		</bndbox>
	</object>
	<object>
		<name>vehicle</name>
		<pose>overlook</pose>
		<truncated>0</truncated>
		<difficult>0</difficult>
		<bndbox>
			<xmin>389</xmin>
			<ymin>574</ymin>
			<xmax>428</xmax>
			<ymax>622</ymax>
		</bndbox>
	</object>
	<object>
		<name>vehicle</name>
		<pose>overlook</pose>
		<truncated>0</truncated>
		<difficult>0</difficult>
		<bndbox>
			<xmin>263</xmin>
			<ymin>806</ymin>
			<xmax>302</xmax>
			<ymax>856</ymax>
		</bndbox>
	</object>
	<object>
		<name>vehicle</name>
		<pose>overlook</pose>
		<truncated>0</truncated>
		<difficult>0</difficult>
		<bndbox>
			<xmin>316</xmin>
			<ymin>855</ymin>
			<xmax>363</xmax>
			<ymax>891</ymax>
		</bndbox>
	</object>
</annotation>
