<annotation>
	<folder>OPTIMAL_Z</folder>
	<filename>21577.jpg</filename>
	<source>
		<database>The OPTIMAL_Z Database</database>
		<annotation>OPTIMAL_Z_anno</annotation>
		<image>OPTIMAL_Z_img</image>
		<flickrid>NULL</flickrid>
	</source>
	<owner>
		<flickrid>NULL</flickrid>
		<name>snail_crowling</name>
	</owner>
	<size>
		<width>1840</width>
		<height>1528</height>
		<depth>3</depth>
	</size>
	<segmented>0</segmented>
	<object>
		<name>ground track field</name>
		<pose>overlook</pose>
		<truncated>0</truncated>
		<difficult>0</difficult>
		<bndbox>
			<xmin>396</xmin>
			<ymin>477</ymin>
			<xmax>565</xmax>
			<ymax>762</ymax>
		</bndbox>
	</object>
	<object>
		<name>basketball court</name>
		<pose>overlook</pose>
		<truncated>0</truncated>
		<difficult>0</difficult>
		<bndbox>
			<xmin>424</xmin>
			<ymin>641</ymin>
			<xmax>545</xmax>
			<ymax>710</ymax>
		</bndbox>
	</object>
	<object>
		<name>basketball court</name>
		<pose>overlook</pose>
		<truncated>0</truncated>
		<difficult>0</difficult>
		<bndbox>
			<xmin>427</xmin>
			<ymin>530</ymin>
			<xmax>543</xmax>
			<ymax>598</ymax>
		</bndbox>
	</object>
</annotation>
